{
  "db_name": "PostgreSQL",
  "query": "\n            SELECT COALESCE(SUM(amount)::BIGINT, 0) as \"total!\"\n            FROM landed_cost_lines\n            WHERE tenant_id = $1 AND document_id = $2\n            ",
  "describe": {
    "columns": [
      {
        "ordinal": 0,
        "name": "total!",
        "type_info": "Int8"
      }
    ],
    "parameters": {
      "Left": [
        "Uuid",
        "Uuid"
      ]
    },
    "nullable": [
      null
    ]
  },
  "hash": "9b96e2a6596f1d90a22127990bfcf024b4e23b11ca627f0786b56cd88a05d679"
}
